Metadata-Version: 1.0
Name: taskall
Version: 0.1.1
Summary: Taskall is a Python module which simplifies the chore of creating and executing tasks in parallel
Home-page: https://github.com/srafehi/taskall
Author: UNKNOWN
Author-email: UNKNOWN
License: MIT
Keywords: parallel,pool,multiprocessing
Platform: UNKNOWN
